CHANGELOG.md
README.md
asherah/__init__.py
asherah/asherah.py
asherah/exceptions.py
asherah/libasherah/libasherah-arm64.dylib
asherah/libasherah/libasherah-arm64.so
asherah/libasherah/libasherah-x64.dylib
asherah/libasherah/libasherah-x64.so
asherah/py.typed
asherah/scripts/download-libasherah.sh
asherah/types.py
asherah-0.3.9.dist-info/LICENSE
asherah-0.3.9.dist-info/METADATA
asherah-0.3.9.dist-info/WHEEL
asherah-0.3.9.dist-info/RECORD
