Metadata-Version: 2.1
Name: asherah
Version: 0.3.9
Summary: Asherah envelope encryption and key rotation library
Home-page: https://github.com/godaddy/asherah-python/
License: MIT
Keywords: encryption
Author: Jeremiah Gowdy
Author-email: jeremiah@gowdy.me
Maintainer: GoDaddy
Maintainer-email: oss@godaddy.com
Requires-Python: >=3.10,<4.0
Classifier: Development Status :: 4 - Beta
Classifier: Intended Audience :: Developers
Classifier: License :: OSI Approved :: MIT License
Classifier: Operating System :: MacOS :: MacOS X
Classifier: Operating System :: POSIX :: Linux
Classifier: Programming Language :: Python :: 3
Classifier: Programming Language :: Python :: 3.10
Classifier: Programming Language :: Python :: 3.11
Classifier: Programming Language :: Python :: 3.12
Classifier: Programming Language :: Python :: 3.7
Classifier: Programming Language :: Python :: 3.8
Classifier: Programming Language :: Python :: 3.9
Classifier: Topic :: Security :: Cryptography
Classifier: Topic :: Software Development :: Libraries :: Python Modules
Classifier: Typing :: Typed
Requires-Dist: cobhan (>=0.4.3,<0.5.0)
Project-URL: Repository, https://github.com/godaddy/asherah-python/
